README.md
setup.py
htjs_apisdk/__init__.py
htjs_apisdk/_api_sdk.py
htjs_apisdk.egg-info/PKG-INFO
htjs_apisdk.egg-info/SOURCES.txt
htjs_apisdk.egg-info/dependency_links.txt
htjs_apisdk.egg-info/requires.txt
htjs_apisdk.egg-info/top_level.txt