Metadata-Version: 2.1
Name: htjs-apisdk
Version: 1.0.3
Summary: HtjsApiClient
Home-page: UNKNOWN
Author: Mu Xiaofei
Author-email: htjs.net@gmail.com
License: UNKNOWN
Keywords: htjs,htjs.net
Platform: UNKNOWN
Classifier: Programming Language :: Python :: 2
Classifier: Programming Language :: Python :: 2.6
Classifier: Programming Language :: Python :: 2.7
Classifier: Programming Language :: Python :: 3
Classifier: Programming Language :: Python :: 3.6
Classifier: Programming Language :: Python :: 3.7
Classifier: License :: OSI Approved :: MIT License
Classifier: Operating System :: OS Independent
